.coveragerc
.env
.flake8
.gitignore
.pre-commit-config.yaml
CODEOWNERS
Dockerfile
MANIFEST.in
README.md
docker-compose.yml
manage.py
pyproject.toml
pytest.ini
setup.cfg
setup.py
sonar-project.properties
.github/workflows/github-actions.yml
.github/workflows/publish-actions.yml
baseapp/README.md
baseapp/__init__.py
baseapp/activity_log/README.md
baseapp/activity_log/__init__.py
baseapp/activity_log/admin.py
baseapp/activity_log/apps.py
baseapp/activity_log/context.py
baseapp/activity_log/middleware.py
baseapp/activity_log/models.py
baseapp/activity_log/permissions.py
baseapp/activity_log/graphql/__init__.py
baseapp/activity_log/graphql/filters.py
baseapp/activity_log/graphql/interfaces.py
baseapp/activity_log/graphql/object_types.py
baseapp/activity_log/graphql/queries.py
baseapp/activity_log/graphql/subscriptions.py
baseapp/activity_log/migrations/0001_initial.py
baseapp/activity_log/migrations/0002_auto_20241216_1804.py
baseapp/activity_log/migrations/0003_delete_activitylog_activitylog.py
baseapp/activity_log/migrations/__init__.py
baseapp/activity_log/tests/__init__.py
baseapp/activity_log/tests/conftest.py
baseapp/activity_log/tests/factories.py
baseapp/activity_log/tests/test_graphql_mutations.py
baseapp/activity_log/tests/test_graphql_queries.py
baseapp/content_feed/__init__.py
baseapp/content_feed/admin.py
baseapp/content_feed/apps.py
baseapp/content_feed/models.py
baseapp/content_feed/graphql/__init__.py
baseapp/content_feed/graphql/filters.py
baseapp/content_feed/graphql/mutations.py
baseapp/content_feed/graphql/object_types.py
baseapp/content_feed/graphql/queries.py
baseapp/content_feed/migrations/0001_initial.py
baseapp/content_feed/migrations/0002_contentpostimage.py
baseapp/content_feed/migrations/0003_alter_contentpostimage_image.py
baseapp/content_feed/migrations/0004_alter_contentpostimage_post.py
baseapp/content_feed/migrations/0005_contentpost_is_reactions_enabled_and_more.py
baseapp/content_feed/migrations/__init__.py
baseapp_backend.egg-info/PKG-INFO
baseapp_backend.egg-info/SOURCES.txt
baseapp_backend.egg-info/dependency_links.txt
baseapp_backend.egg-info/requires.txt
baseapp_backend.egg-info/top_level.txt
