Metadata-Version: 2.1
Name: baseapp-backend
Version: 0.0.50
Summary: BaseApp
Home-page: https://github.com/silverlogic/baseapp-backend
Author: The SilverLogic
Author-email: dev@tsl.io
License: BSD-3-Clause  # Example license
Platform: UNKNOWN
Requires-Python: >=3.11
Provides-Extra: auth
Provides-Extra: referrals
Provides-Extra: graphql
Provides-Extra: pages
Provides-Extra: payments
Provides-Extra: notifications
Provides-Extra: urlshortening
Provides-Extra: messagetemplates
Provides-Extra: wagtail
Provides-Extra: socialauth
Provides-Extra: pdf
